envoy/code/check/__init__.py
envoy/code/check/checker.py
envoy/code/check/cmd.py
envoy/code/check/exceptions.py
envoy/code/check/interface.py
envoy/code/check/py.typed
envoy/code/check/typing.py
envoy/code/check/abstract/__init__.py
envoy/code/check/abstract/base.py
envoy/code/check/abstract/changelog.py
envoy/code/check/abstract/checker.py
envoy/code/check/abstract/extensions.py
envoy/code/check/abstract/flake8.py
envoy/code/check/abstract/glint.py
envoy/code/check/abstract/gofmt.py
envoy/code/check/abstract/rst.py
envoy/code/check/abstract/runtime_guards.py
envoy/code/check/abstract/shellcheck.py
envoy/code/check/abstract/yamllint.py
envoy/code/check/abstract/yapf.py
envoy.code.check-0.5.14.dist-info/METADATA
envoy.code.check-0.5.14.dist-info/WHEEL
envoy.code.check-0.5.14.dist-info/entry_points.txt
envoy.code.check-0.5.14.dist-info/namespace_packages.txt
envoy.code.check-0.5.14.dist-info/top_level.txt
envoy.code.check-0.5.14.dist-info/RECORD
