Metadata-Version: 2.1
Name: envoy.code.check
Version: 0.5.14
Summary: "Code checker used in Envoy proxy's CI"
Home-page: https://github.com/envoyproxy/toolshed/tree/main/envoy.code.check
Author: Ryan Northey
Author-email: ryan@synca.io
Maintainer: Ryan Northey
Maintainer-email: ryan@synca.io
License: Apache Software License 2.0
Requires-Python: >=3.10.0
Requires-Dist: abstracts (>=0.0.12)
Requires-Dist: aio.core (>=0.10.5)
Requires-Dist: aio.run.checker (>=0.5.8)
Requires-Dist: envoy.base.utils (>=0.4.7)
Requires-Dist: flake8 (>=6)
Requires-Dist: packaging (>=23.0)
Requires-Dist: types-pyyaml
Requires-Dist: yamllint
Requires-Dist: yapf
